leads/__init__.py
leads/callback.py
leads/constant.py
leads/context.py
leads/data.py
leads/event.py
leads/leads.py
leads/logger.py
leads/ltm.py
leads/os.py
leads/registry.py
leads/sft.py
leads/types.py
leads/_ltm/core
leads/comm/__init__.py
leads/comm/prototype.py
leads/comm/client/__init__.py
leads/comm/client/client.py
leads/comm/server/__init__.py
leads/comm/server/server.py
leads/config/__init__.py
leads/config/registry.py
leads/config/template.py
leads/data_persistence/__init__.py
leads/data_persistence/core.py
leads/data_persistence/_computational/__init__.py
leads/data_persistence/analyzer/__init__.py
leads/data_persistence/analyzer/inference.py
leads/data_persistence/analyzer/jarvis.py
leads/data_persistence/analyzer/preprocess.py
leads/data_persistence/analyzer/processor.py
leads/data_persistence/analyzer/utils.py
leads/dt/__init__.py
leads/dt/controller.py
leads/dt/device.py
leads/dt/odometer.py
leads/dt/predefined_tags.py
leads/dt/registry.py
leads/plugin/__init__.py
leads/plugin/abs.py
leads/plugin/atbs.py
leads/plugin/dtcs.py
leads/plugin/ebi.py
leads/plugin/plugin.py
leads_arduino/__init__.py
leads_arduino/accelerometer.py
leads_arduino/arduino_micro.py
leads_arduino/arduino_nano.py
leads_arduino/arduino_proto.py
leads_arduino/pedal.py
leads_arduino/voltage_sensor.py
leads_arduino/wheel_speed_sensor.py
leads_audio/__init__.py
leads_audio/prototype.py
leads_audio/system.py
leads_audio/assets/confirm.mp3
leads_audio/assets/direction-indicator-off.mp3
leads_audio/assets/direction-indicator-on.mp3
leads_audio/assets/warning.mp3
leads_can/__init__.py
leads_can/obd.py
leads_can/prototype.py
leads_comm_serial/__init__.py
leads_comm_serial/connection.py
leads_comm_serial/identity.py
leads_comm_serial/sobd/__init__.py
leads_comm_serial/sobd/sobd.py
leads_emulation/__init__.py
leads_emulation/replay.py
leads_gpio/__init__.py
leads_gpio/button.py
leads_gpio/cpu_monitor.py
leads_gpio/gps_receiver.py
leads_gpio/led.py
leads_gpio/led_group.py
leads_gpio/types.py
leads-0.9.7.dist-info/METADATA
leads-0.9.7.dist-info/WHEEL
leads-0.9.7.dist-info/entry_points.txt
leads-0.9.7.dist-info/licenses/LICENSE
leads-0.9.7.dist-info/RECORD
