Metadata-Version: 2.4
Name: leads
Version: 0.9.7
Summary: Lightweight Embedded Assisted Driving System
Project-URL: Homepage, https://leads.projectneura.org
Project-URL: Documentation, https://leads-docs.projectneura.org
Project-URL: Repository, https://github.com/ProjectNeura/LEADS
Author-email: Project Neura <central@projectneura.org>
License-Expression: Apache-2.0
License-File: LICENSE
Requires-Python: >=3.12
Requires-Dist: numpy
Requires-Dist: pandas
Provides-Extra: gpio
Requires-Dist: customtkinter; extra == 'gpio'
Requires-Dist: gpiozero; extra == 'gpio'
Requires-Dist: lgpio; extra == 'gpio'
Requires-Dist: opencv-python-headless; extra == 'gpio'
Requires-Dist: pillow; extra == 'gpio'
Requires-Dist: pynmea2; extra == 'gpio'
Requires-Dist: pysdl2; extra == 'gpio'
Requires-Dist: pysdl2-dll; extra == 'gpio'
Requires-Dist: pyserial; extra == 'gpio'
Requires-Dist: screeninfo; extra == 'gpio'
Provides-Extra: standard
Requires-Dist: customtkinter; extra == 'standard'
Requires-Dist: gpiozero; extra == 'standard'
Requires-Dist: opencv-python-headless; extra == 'standard'
Requires-Dist: pillow; extra == 'standard'
Requires-Dist: pynmea2; extra == 'standard'
Requires-Dist: pysdl2; extra == 'standard'
Requires-Dist: pysdl2-dll; extra == 'standard'
Requires-Dist: pyserial; extra == 'standard'
Requires-Dist: screeninfo; extra == 'standard'
Provides-Extra: vec
Requires-Dist: customtkinter; extra == 'vec'
Requires-Dist: gpiozero; extra == 'vec'
Requires-Dist: lgpio; extra == 'vec'
Requires-Dist: opencv-python-headless; extra == 'vec'
Requires-Dist: pillow; extra == 'vec'
Requires-Dist: pynmea2; extra == 'vec'
Requires-Dist: pynput; extra == 'vec'
Requires-Dist: pysdl2; extra == 'vec'
Requires-Dist: pysdl2-dll; extra == 'vec'
Requires-Dist: pyserial; extra == 'vec'
Requires-Dist: screeninfo; extra == 'vec'
Provides-Extra: vec-dp
Requires-Dist: customtkinter; extra == 'vec-dp'
Requires-Dist: gpiozero; extra == 'vec-dp'
Requires-Dist: matplotlib; extra == 'vec-dp'
Requires-Dist: opencv-python-headless; extra == 'vec-dp'
Requires-Dist: pillow; extra == 'vec-dp'
Requires-Dist: pynmea2; extra == 'vec-dp'
Requires-Dist: pysdl2; extra == 'vec-dp'
Requires-Dist: pysdl2-dll; extra == 'vec-dp'
Requires-Dist: pyserial; extra == 'vec-dp'
Requires-Dist: pyyaml; extra == 'vec-dp'
Requires-Dist: screeninfo; extra == 'vec-dp'
Provides-Extra: vec-no-gpio
Requires-Dist: customtkinter; extra == 'vec-no-gpio'
Requires-Dist: gpiozero; extra == 'vec-no-gpio'
Requires-Dist: opencv-python-headless; extra == 'vec-no-gpio'
Requires-Dist: pillow; extra == 'vec-no-gpio'
Requires-Dist: pynmea2; extra == 'vec-no-gpio'
Requires-Dist: pynput; extra == 'vec-no-gpio'
Requires-Dist: pysdl2; extra == 'vec-no-gpio'
Requires-Dist: pysdl2-dll; extra == 'vec-no-gpio'
Requires-Dist: pyserial; extra == 'vec-no-gpio'
Requires-Dist: screeninfo; extra == 'vec-no-gpio'
Provides-Extra: vec-rc
Requires-Dist: customtkinter; extra == 'vec-rc'
Requires-Dist: fastapi[standard]; extra == 'vec-rc'
Requires-Dist: gpiozero; extra == 'vec-rc'
Requires-Dist: opencv-python-headless; extra == 'vec-rc'
Requires-Dist: pillow; extra == 'vec-rc'
Requires-Dist: pynmea2; extra == 'vec-rc'
Requires-Dist: pysdl2; extra == 'vec-rc'
Requires-Dist: pysdl2-dll; extra == 'vec-rc'
Requires-Dist: pyserial; extra == 'vec-rc'
Requires-Dist: screeninfo; extra == 'vec-rc'
